{
  "pull": {
    "url": "https://api.github.com/repos/NVIDIA/cutlass/pulls/2172",
    "id": 2391704060,
    "node_id": "PR_kwDOBrVDM86OjoH8",
    "html_url": "https://github.com/NVIDIA/cutlass/pull/2172",
    "diff_url": "https://github.com/NVIDIA/cutlass/pull/2172.diff",
    "patch_url": "https://github.com/NVIDIA/cutlass/pull/2172.patch",
    "issue_url": "https://api.github.com/repos/NVIDIA/cutlass/issues/2172",
    "number": 2172,
    "state": "closed",
    "locked": false,
    "title": "Fix SM90 beta=1 hang and stream-K launch errors",
    "user": {
      "login": "jackkosaian",
      "id": 5831848,
      "node_id": "MDQ6VXNlcjU4MzE4NDg=",
      "avatar_url": "https://avatars.githubusercontent.com/u/5831848?v=4",
      "gravatar_id": "",
      "url": "https://api.github.com/users/jackkosaian",
      "html_url": "https://github.com/jackkosaian",
      "followers_url": "https://api.github.com/users/jackkosaian/followers",
      "following_url": "https://api.github.com/users/jackkosaian/following{/other_user}",
      "gists_url": "https://api.github.com/users/jackkosaian/gists{/gist_id}",
      "starred_url": "https://api.github.com/users/jackkosaian/starred{/owner}{/repo}",
      "subscriptions_url": "https://api.github.com/users/jackkosaian/subscriptions",
      "organizations_url": "https://api.github.com/users/jackkosaian/orgs",
      "repos_url": "https://api.github.com/users/jackkosaian/repos",
      "events_url": "https://api.github.com/users/jackkosaian/events{/privacy}",
      "received_events_url": "https://api.github.com/users/jackkosaian/received_events",
      "type": "User",
      "user_view_type": "public",
      "site_admin": false
    },
    "body": "Fixes #2157 and #2152 ",
    "created_at": "2025-03-13T17:54:24Z",
    "updated_at": "2025-03-13T19:04:43Z",
    "closed_at": "2025-03-13T18:07:37Z",
    "merged_at": "2025-03-13T18:07:37Z",
    "merge_commit_sha": "6c6b78550e0752309c1f85dc9c1f6e636c8d751c",
    "assignees": [],
    "requested_reviewers": [],
    "requested_teams": [],
    "labels": [],
    "milestone": null,
    "draft": false,
    "commits_url": "https://api.github.com/repos/NVIDIA/cutlass/pulls/2172/commits",
    "review_comments_url": "https://api.github.com/repos/NVIDIA/cutlass/pulls/2172/comments",
    "review_comment_url": "https://api.github.com/repos/NVIDIA/cutlass/pulls/comments{/number}",
    "comments_url": "https://api.github.com/repos/NVIDIA/cutlass/issues/2172/comments",
    "statuses_url": "https://api.github.com/repos/NVIDIA/cutlass/statuses/4ebb8f39de262dd34f690fe35105ae93394c6936",
    "head": {
      "label": "jackkosaian:fix/sm90-hang-and-sk-error",
      "ref": "fix/sm90-hang-and-sk-error",
      "sha": "4ebb8f39de262dd34f690fe35105ae93394c6936",
      "user": {
        "login": "jackkosaian",
        "id": 5831848,
        "node_id": "MDQ6VXNlcjU4MzE4NDg=",
        "avatar_url": "https://avatars.githubusercontent.com/u/5831848?v=4",
        "gravatar_id": "",
        "url": "https://api.github.com/users/jackkosaian",
        "html_url": "https://github.com/jackkosaian",
        "followers_url": "https://api.github.com/users/jackkosaian/followers",
        "following_url": "https://api.github.com/users/jackkosaian/following{/other_user}",
        "gists_url": "https://api.github.com/users/jackkosaian/gists{/gist_id}",
        "starred_url": "https://api.github.com/users/jackkosaian/starred{/owner}{/repo}",
        "subscriptions_url": "https://api.github.com/users/jackkosaian/subscriptions",
        "organizations_url": "https://api.github.com/users/jackkosaian/orgs",
        "repos_url": "https://api.github.com/users/jackkosaian/repos",
        "events_url": "https://api.github.com/users/jackkosaian/events{/privacy}",
        "received_events_url": "https://api.github.com/users/jackkosaian/received_events",
        "type": "User",
        "user_view_type": "public",
        "site_admin": false
      },
      "repo": {
        "id": 504499999,
        "node_id": "R_kgDOHhIPHw",
        "name": "cutlass",
        "full_name": "jackkosaian/cutlass",
        "private": false,
        "owner": {
          "login": "jackkosaian",
          "id": 5831848,
          "node_id": "MDQ6VXNlcjU4MzE4NDg=",
          "avatar_url": "https://avatars.githubusercontent.com/u/5831848?v=4",
          "gravatar_id": "",
          "url": "https://api.github.com/users/jackkosaian",
          "html_url": "https://github.com/jackkosaian",
          "followers_url": "https://api.github.com/users/jackkosaian/followers",
          "following_url": "https://api.github.com/users/jackkosaian/following{/other_user}",
          "gists_url": "https://api.github.com/users/jackkosaian/gists{/gist_id}",
          "starred_url": "https://api.github.com/users/jackkosaian/starred{/owner}{/repo}",
          "subscriptions_url": "https://api.github.com/users/jackkosaian/subscriptions",
          "organizations_url": "https://api.github.com/users/jackkosaian/orgs",
          "repos_url": "https://api.github.com/users/jackkosaian/repos",
          "events_url": "https://api.github.com/users/jackkosaian/events{/privacy}",
          "received_events_url": "https://api.github.com/users/jackkosaian/received_events",
          "type": "User",
          "user_view_type": "public",
          "site_admin": false
        },
        "html_url": "https://github.com/jackkosaian/cutlass",
        "description": "CUDA Templates for Linear Algebra Subroutines",
        "fork": true,
        "url": "https://api.github.com/repos/jackkosaian/cutlass",
        "forks_url": "https://api.github.com/repos/jackkosaian/cutlass/forks",
        "keys_url": "https://api.github.com/repos/jackkosaian/cutlass/keys{/key_id}",
        "collaborators_url": "https://api.github.com/repos/jackkosaian/cutlass/collaborators{/collaborator}",
        "teams_url": "https://api.github.com/repos/jackkosaian/cutlass/teams",
        "hooks_url": "https://api.github.com/repos/jackkosaian/cutlass/hooks",
        "issue_events_url": "https://api.github.com/repos/jackkosaian/cutlass/issues/events{/number}",
        "events_url": "https://api.github.com/repos/jackkosaian/cutlass/events",
        "assignees_url": "https://api.github.com/repos/jackkosaian/cutlass/assignees{/user}",
        "branches_url": "https://api.github.com/repos/jackkosaian/cutlass/branches{/branch}",
        "tags_url": "https://api.github.com/repos/jackkosaian/cutlass/tags",
        "blobs_url": "https://api.github.com/repos/jackkosaian/cutlass/git/blobs{/sha}",
        "git_tags_url": "https://api.github.com/repos/jackkosaian/cutlass/git/tags{/sha}",
        "git_refs_url": "https://api.github.com/repos/jackkosaian/cutlass/git/refs{/sha}",
        "trees_url": "https://api.github.com/repos/jackkosaian/cutlass/git/trees{/sha}",
        "statuses_url": "https://api.github.com/repos/jackkosaian/cutlass/statuses/{sha}",
        "languages_url": "https://api.github.com/repos/jackkosaian/cutlass/languages",
        "stargazers_url": "https://api.github.com/repos/jackkosaian/cutlass/stargazers",
        "contributors_url": "https://api.github.com/repos/jackkosaian/cutlass/contributors",
        "subscribers_url": "https://api.github.com/repos/jackkosaian/cutlass/subscribers",
        "subscription_url": "https://api.github.com/repos/jackkosaian/cutlass/subscription",
        "commits_url": "https://api.github.com/repos/jackkosaian/cutlass/commits{/sha}",
        "git_commits_url": "https://api.github.com/repos/jackkosaian/cutlass/git/commits{/sha}",
        "comments_url": "https://api.github.com/repos/jackkosaian/cutlass/comments{/number}",
        "issue_comment_url": "https://api.github.com/repos/jackkosaian/cutlass/issues/comments{/number}",
        "contents_url": "https://api.github.com/repos/jackkosaian/cutlass/contents/{+path}",
        "compare_url": "https://api.github.com/repos/jackkosaian/cutlass/compare/{base}...{head}",
        "merges_url": "https://api.github.com/repos/jackkosaian/cutlass/merges",
        "archive_url": "https://api.github.com/repos/jackkosaian/cutlass/{archive_format}{/ref}",
        "downloads_url": "https://api.github.com/repos/jackkosaian/cutlass/downloads",
        "issues_url": "https://api.github.com/repos/jackkosaian/cutlass/issues{/number}",
        "pulls_url": "https://api.github.com/repos/jackkosaian/cutlass/pulls{/number}",
        "milestones_url": "https://api.github.com/repos/jackkosaian/cutlass/milestones{/number}",
        "notifications_url": "https://api.github.com/repos/jackkosaian/cutlass/notifications{?since,all,participating}",
        "labels_url": "https://api.github.com/repos/jackkosaian/cutlass/labels{/name}",
        "releases_url": "https://api.github.com/repos/jackkosaian/cutlass/releases{/id}",
        "deployments_url": "https://api.github.com/repos/jackkosaian/cutlass/deployments",
        "created_at": "2022-06-17T10:56:20Z",
        "updated_at": "2025-09-17T20:52:00Z",
        "pushed_at": "2025-09-17T20:57:11Z",
        "git_url": "git://github.com/jackkosaian/cutlass.git",
        "ssh_url": "git@github.com:jackkosaian/cutlass.git",
        "clone_url": "https://github.com/jackkosaian/cutlass.git",
        "svn_url": "https://github.com/jackkosaian/cutlass",
        "homepage": "",
        "size": 54867,
        "stargazers_count": 0,
        "watchers_count": 0,
        "language": "C++",
        "has_issues": false,
        "has_projects": true,
        "has_downloads": true,
        "has_wiki": true,
        "has_pages": false,
        "has_discussions": false,
        "forks_count": 0,
        "mirror_url": null,
        "archived": false,
        "disabled": false,
        "open_issues_count": 0,
        "license": {
          "key": "other",
          "name": "Other",
          "spdx_id": "NOASSERTION",
          "url": null,
          "node_id": "MDc6TGljZW5zZTA="
        },
        "allow_forking": true,
        "is_template": false,
        "web_commit_signoff_required": false,
        "has_pull_requests": true,
        "pull_request_creation_policy": "all",
        "topics": [],
        "visibility": "public",
        "forks": 0,
        "open_issues": 0,
        "watchers": 0,
        "default_branch": "main"
      }
    },
    "base": {
      "label": "NVIDIA:main",
      "ref": "main",
      "sha": "06e560d98a5fe8acb975db2c4c26817b6c90acb1",
      "user": {
        "login": "NVIDIA",
        "id": 1728152,
        "node_id": "MDEyOk9yZ2FuaXphdGlvbjE3MjgxNTI=",
        "avatar_url": "https://avatars.githubusercontent.com/u/1728152?v=4",
        "gravatar_id": "",
        "url": "https://api.github.com/users/NVIDIA",
        "html_url": "https://github.com/NVIDIA",
        "followers_url": "https://api.github.com/users/NVIDIA/followers",
        "following_url": "https://api.github.com/users/NVIDIA/following{/other_user}",
        "gists_url": "https://api.github.com/users/NVIDIA/gists{/gist_id}",
        "starred_url": "https://api.github.com/users/NVIDIA/starred{/owner}{/repo}",
        "subscriptions_url": "https://api.github.com/users/NVIDIA/subscriptions",
        "organizations_url": "https://api.github.com/users/NVIDIA/orgs",
        "repos_url": "https://api.github.com/users/NVIDIA/repos",
        "events_url": "https://api.github.com/users/NVIDIA/events{/privacy}",
        "received_events_url": "https://api.github.com/users/NVIDIA/received_events",
        "type": "Organization",
        "user_view_type": "public",
        "site_admin": false
      },
      "repo": {
        "id": 112542515,
        "node_id": "MDEwOlJlcG9zaXRvcnkxMTI1NDI1MTU=",
        "name": "cutlass",
        "full_name": "NVIDIA/cutlass",
        "private": false,
        "owner": {
          "login": "NVIDIA",
          "id": 1728152,
          "node_id": "MDEyOk9yZ2FuaXphdGlvbjE3MjgxNTI=",
          "avatar_url": "https://avatars.githubusercontent.com/u/1728152?v=4",
          "gravatar_id": "",
          "url": "https://api.github.com/users/NVIDIA",
          "html_url": "https://github.com/NVIDIA",
          "followers_url": "https://api.github.com/users/NVIDIA/followers",
          "following_url": "https://api.github.com/users/NVIDIA/following{/other_user}",
          "gists_url": "https://api.github.com/users/NVIDIA/gists{/gist_id}",
          "starred_url": "https://api.github.com/users/NVIDIA/starred{/owner}{/repo}",
          "subscriptions_url": "https://api.github.com/users/NVIDIA/subscriptions",
          "organizations_url": "https://api.github.com/users/NVIDIA/orgs",
          "repos_url": "https://api.github.com/users/NVIDIA/repos",
          "events_url": "https://api.github.com/users/NVIDIA/events{/privacy}",
          "received_events_url": "https://api.github.com/users/NVIDIA/received_events",
          "type": "Organization",
          "user_view_type": "public",
          "site_admin": false
        },
        "html_url": "https://github.com/NVIDIA/cutlass",
        "description": "CUDA Templates and Python DSLs for High-Performance Linear Algebra",
        "fork": false,
        "url": "https://api.github.com/repos/NVIDIA/cutlass",
        "forks_url": "https://api.github.com/repos/NVIDIA/cutlass/forks",
        "keys_url": "https://api.github.com/repos/NVIDIA/cutlass/keys{/key_id}",
        "collaborators_url": "https://api.github.com/repos/NVIDIA/cutlass/collaborators{/collaborator}",
        "teams_url": "https://api.github.com/repos/NVIDIA/cutlass/teams",
        "hooks_url": "https://api.github.com/repos/NVIDIA/cutlass/hooks",
        "issue_events_url": "https://api.github.com/repos/NVIDIA/cutlass/issues/events{/number}",
        "events_url": "https://api.github.com/repos/NVIDIA/cutlass/events",
        "assignees_url": "https://api.github.com/repos/NVIDIA/cutlass/assignees{/user}",
        "branches_url": "https://api.github.com/repos/NVIDIA/cutlass/branches{/branch}",
        "tags_url": "https://api.github.com/repos/NVIDIA/cutlass/tags",
        "blobs_url": "https://api.github.com/repos/NVIDIA/cutlass/git/blobs{/sha}",
        "git_tags_url": "https://api.github.com/repos/NVIDIA/cutlass/git/tags{/sha}",
        "git_refs_url": "https://api.github.com/repos/NVIDIA/cutlass/git/refs{/sha}",
        "trees_url": "https://api.github.com/repos/NVIDIA/cutlass/git/trees{/sha}",
        "statuses_url": "https://api.github.com/repos/NVIDIA/cutlass/statuses/{sha}",
        "languages_url": "https://api.github.com/repos/NVIDIA/cutlass/languages",
        "stargazers_url": "https://api.github.com/repos/NVIDIA/cutlass/stargazers",
        "contributors_url": "https://api.github.com/repos/NVIDIA/cutlass/contributors",
        "subscribers_url": "https://api.github.com/repos/NVIDIA/cutlass/subscribers",
        "subscription_url": "https://api.github.com/repos/NVIDIA/cutlass/subscription",
        "commits_url": "https://api.github.com/repos/NVIDIA/cutlass/commits{/sha}",
        "git_commits_url": "https://api.github.com/repos/NVIDIA/cutlass/git/commits{/sha}",
        "comments_url": "https://api.github.com/repos/NVIDIA/cutlass/comments{/number}",
        "issue_comment_url": "https://api.github.com/repos/NVIDIA/cutlass/issues/comments{/number}",
        "contents_url": "https://api.github.com/repos/NVIDIA/cutlass/contents/{+path}",
        "compare_url": "https://api.github.com/repos/NVIDIA/cutlass/compare/{base}...{head}",
        "merges_url": "https://api.github.com/repos/NVIDIA/cutlass/merges",
        "archive_url": "https://api.github.com/repos/NVIDIA/cutlass/{archive_format}{/ref}",
        "downloads_url": "https://api.github.com/repos/NVIDIA/cutlass/downloads",
        "issues_url": "https://api.github.com/repos/NVIDIA/cutlass/issues{/number}",
        "pulls_url": "https://api.github.com/repos/NVIDIA/cutlass/pulls{/number}",
        "milestones_url": "https://api.github.com/repos/NVIDIA/cutlass/milestones{/number}",
        "notifications_url": "https://api.github.com/repos/NVIDIA/cutlass/notifications{?since,all,participating}",
        "labels_url": "https://api.github.com/repos/NVIDIA/cutlass/labels{/name}",
        "releases_url": "https://api.github.com/repos/NVIDIA/cutlass/releases{/id}",
        "deployments_url": "https://api.github.com/repos/NVIDIA/cutlass/deployments",
        "created_at": "2017-11-30T00:11:24Z",
        "updated_at": "2026-05-15T21:07:57Z",
        "pushed_at": "2026-05-13T03:39:02Z",
        "git_url": "git://github.com/NVIDIA/cutlass.git",
        "ssh_url": "git@github.com:NVIDIA/cutlass.git",
        "clone_url": "https://github.com/NVIDIA/cutlass.git",
        "svn_url": "https://github.com/NVIDIA/cutlass",
        "homepage": "https://docs.nvidia.com/cutlass/index.html",
        "size": 67022,
        "stargazers_count": 9728,
        "watchers_count": 9728,
        "language": "C++",
        "has_issues": true,
        "has_projects": true,
        "has_downloads": true,
        "has_wiki": true,
        "has_pages": true,
        "has_discussions": true,
        "forks_count": 1855,
        "mirror_url": null,
        "archived": false,
        "disabled": false,
        "open_issues_count": 640,
        "license": {
          "key": "other",
          "name": "Other",
          "spdx_id": "NOASSERTION",
          "url": null,
          "node_id": "MDc6TGljZW5zZTA="
        },
        "allow_forking": true,
        "is_template": false,
        "web_commit_signoff_required": false,
        "has_pull_requests": true,
        "pull_request_creation_policy": "all",
        "topics": [
          "cpp",
          "cuda",
          "deep-learning",
          "deep-learning-library",
          "gpu",
          "nvidia",
          "python"
        ],
        "visibility": "public",
        "forks": 1855,
        "open_issues": 640,
        "watchers": 9728,
        "default_branch": "main"
      }
    },
    "_links": {
      "self": {
        "href": "https://api.github.com/repos/NVIDIA/cutlass/pulls/2172"
      },
      "html": {
        "href": "https://github.com/NVIDIA/cutlass/pull/2172"
      },
      "issue": {
        "href": "https://api.github.com/repos/NVIDIA/cutlass/issues/2172"
      },
      "comments": {
        "href": "https://api.github.com/repos/NVIDIA/cutlass/issues/2172/comments"
      },
      "review_comments": {
        "href": "https://api.github.com/repos/NVIDIA/cutlass/pulls/2172/comments"
      },
      "review_comment": {
        "href": "https://api.github.com/repos/NVIDIA/cutlass/pulls/comments{/number}"
      },
      "commits": {
        "href": "https://api.github.com/repos/NVIDIA/cutlass/pulls/2172/commits"
      },
      "statuses": {
        "href": "https://api.github.com/repos/NVIDIA/cutlass/statuses/4ebb8f39de262dd34f690fe35105ae93394c6936"
      }
    },
    "author_association": "COLLABORATOR",
    "auto_merge": null,
    "assignee": null,
    "active_lock_reason": null,
    "merged": true,
    "mergeable": null,
    "rebaseable": null,
    "mergeable_state": "unknown",
    "merged_by": {
      "login": "kerrmudgeon",
      "id": 11259,
      "node_id": "MDQ6VXNlcjExMjU5",
      "avatar_url": "https://avatars.githubusercontent.com/u/11259?v=4",
      "gravatar_id": "",
      "url": "https://api.github.com/users/kerrmudgeon",
      "html_url": "https://github.com/kerrmudgeon",
      "followers_url": "https://api.github.com/users/kerrmudgeon/followers",
      "following_url": "https://api.github.com/users/kerrmudgeon/following{/other_user}",
      "gists_url": "https://api.github.com/users/kerrmudgeon/gists{/gist_id}",
      "starred_url": "https://api.github.com/users/kerrmudgeon/starred{/owner}{/repo}",
      "subscriptions_url": "https://api.github.com/users/kerrmudgeon/subscriptions",
      "organizations_url": "https://api.github.com/users/kerrmudgeon/orgs",
      "repos_url": "https://api.github.com/users/kerrmudgeon/repos",
      "events_url": "https://api.github.com/users/kerrmudgeon/events{/privacy}",
      "received_events_url": "https://api.github.com/users/kerrmudgeon/received_events",
      "type": "User",
      "user_view_type": "public",
      "site_admin": false
    },
    "comments": 1,
    "review_comments": 0,
    "maintainer_can_modify": false,
    "commits": 2,
    "additions": 93,
    "deletions": 64,
    "changed_files": 4
  },
  "files": [
    {
      "sha": "73ee5055b5bbe9f19001be5a0a3d4e67260b1a0d",
      "filename": "include/cutlass/gemm/kernel/sm90_gemm_array_tma_warpspecialized_cooperative.hpp",
      "status": "modified",
      "additions": 2,
      "deletions": 2,
      "changes": 4,
      "blob_url": "https://github.com/NVIDIA/cutlass/blob/4ebb8f39de262dd34f690fe35105ae93394c6936/include%2Fcutlass%2Fgemm%2Fkernel%2Fsm90_gemm_array_tma_warpspecialized_cooperative.hpp",
      "raw_url": "https://github.com/NVIDIA/cutlass/raw/4ebb8f39de262dd34f690fe35105ae93394c6936/include%2Fcutlass%2Fgemm%2Fkernel%2Fsm90_gemm_array_tma_warpspecialized_cooperative.hpp",
      "contents_url": "https://api.github.com/repos/NVIDIA/cutlass/contents/include%2Fcutlass%2Fgemm%2Fkernel%2Fsm90_gemm_array_tma_warpspecialized_cooperative.hpp?ref=4ebb8f39de262dd34f690fe35105ae93394c6936",
      "patch": "@@ -661,9 +661,9 @@ class GemmUniversal<\n           // Converge before issuing tensormap fence release since fence is aligned\n           __syncwarp();\n           collective_epilogue.template tensormaps_cp_fence_release<IsEpiLoad>(shared_storage.tensormaps.epilogue, epi_load_tensormap, 0);\n-        }\n \n-        load_order_barrier.wait();\n+          load_order_barrier.wait();\n+        }\n \n         while (work_tile_info.is_valid()) {\n           int32_t curr_batch = work_tile_info.L_idx;"
    },
    {
      "sha": "882974eef1c145c7271262a7c37e1c0b9f0cfeff",
      "filename": "include/cutlass/gemm/kernel/sm90_gemm_array_tma_warpspecialized_pingpong.hpp",
      "status": "modified",
      "additions": 2,
      "deletions": 2,
      "changes": 4,
      "blob_url": "https://github.com/NVIDIA/cutlass/blob/4ebb8f39de262dd34f690fe35105ae93394c6936/include%2Fcutlass%2Fgemm%2Fkernel%2Fsm90_gemm_array_tma_warpspecialized_pingpong.hpp",
      "raw_url": "https://github.com/NVIDIA/cutlass/raw/4ebb8f39de262dd34f690fe35105ae93394c6936/include%2Fcutlass%2Fgemm%2Fkernel%2Fsm90_gemm_array_tma_warpspecialized_pingpong.hpp",
      "contents_url": "https://api.github.com/repos/NVIDIA/cutlass/contents/include%2Fcutlass%2Fgemm%2Fkernel%2Fsm90_gemm_array_tma_warpspecialized_pingpong.hpp?ref=4ebb8f39de262dd34f690fe35105ae93394c6936",
      "patch": "@@ -693,10 +693,10 @@ class GemmUniversal<\n           // Converge before issuing tensormap fence release since fence is aligned\n           __syncwarp();\n           collective_epilogue.template tensormaps_cp_fence_release<IsEpiLoad>(shared_storage.tensormaps.epilogue, epi_load_tensormap, 0);\n+        \n+          load_order_barrier.wait();\n         }\n \n-        load_order_barrier.wait();\n-\n         while (work_tile_info.is_valid()) {\n           int32_t curr_batch = work_tile_info.L_idx;\n "
    },
    {
      "sha": "9c5d9d476cf36997a5983af4ba02987d21fa1040",
      "filename": "include/cutlass/gemm/kernel/sm90_gemm_tma_warpspecialized_pingpong.hpp",
      "status": "modified",
      "additions": 6,
      "deletions": 1,
      "changes": 7,
      "blob_url": "https://github.com/NVIDIA/cutlass/blob/4ebb8f39de262dd34f690fe35105ae93394c6936/include%2Fcutlass%2Fgemm%2Fkernel%2Fsm90_gemm_tma_warpspecialized_pingpong.hpp",
      "raw_url": "https://github.com/NVIDIA/cutlass/raw/4ebb8f39de262dd34f690fe35105ae93394c6936/include%2Fcutlass%2Fgemm%2Fkernel%2Fsm90_gemm_tma_warpspecialized_pingpong.hpp",
      "contents_url": "https://api.github.com/repos/NVIDIA/cutlass/contents/include%2Fcutlass%2Fgemm%2Fkernel%2Fsm90_gemm_tma_warpspecialized_pingpong.hpp?ref=4ebb8f39de262dd34f690fe35105ae93394c6936",
      "patch": "@@ -548,8 +548,13 @@ class GemmUniversal<\n         // unflushed global memory prior to this instruction\n         cutlass::arch::wait_on_dependent_grids();\n \n-        load_order_barrier.wait();\n+        bool do_load_order_wait = true;\n         while (work_tile_info.is_valid()) {\n+          if (do_load_order_wait) {\n+            load_order_barrier.wait();\n+            do_load_order_wait = false;\n+          }\n+\n           // Compute m_coord, n_coord, l_coord with the post-tiled m-shape and n-shape\n           auto m_coord = idx2crd(work_tile_info.M_idx, shape<2>(gA_mkl));\n           auto n_coord = idx2crd(work_tile_info.N_idx, shape<2>(gB_nkl));"
    },
    {
      "sha": "7ee5b3f87b8ab42ba40437d6b768b2b9882b1441",
      "filename": "include/cutlass/gemm/kernel/tile_scheduler_params.h",
      "status": "modified",
      "additions": 83,
      "deletions": 59,
      "changes": 142,
      "blob_url": "https://github.com/NVIDIA/cutlass/blob/4ebb8f39de262dd34f690fe35105ae93394c6936/include%2Fcutlass%2Fgemm%2Fkernel%2Ftile_scheduler_params.h",
      "raw_url": "https://github.com/NVIDIA/cutlass/raw/4ebb8f39de262dd34f690fe35105ae93394c6936/include%2Fcutlass%2Fgemm%2Fkernel%2Ftile_scheduler_params.h",
      "contents_url": "https://api.github.com/repos/NVIDIA/cutlass/contents/include%2Fcutlass%2Fgemm%2Fkernel%2Ftile_scheduler_params.h?ref=4ebb8f39de262dd34f690fe35105ae93394c6936",
      "patch": "@@ -188,8 +188,8 @@ struct PersistentTileSchedulerSm90Params {\n     KernelHardwareInfo hw_info,\n     int max_swizzle_size,\n     RasterOrderOptions raster_order_option,\n-    bool truncate_by_problem_size=true\n-    , bool bypass_occupancy_calculation=false \n+    bool truncate_by_problem_size=true,\n+    bool bypass_sm90_occupancy_calculation=false\n     ) {\n \n     dim3 problem_blocks = get_tiled_cta_shape_mnl(problem_shape, cta_shape, cluster_shape);\n@@ -199,8 +199,8 @@ struct PersistentTileSchedulerSm90Params {\n       hw_info,\n       max_swizzle_size,\n       raster_order_option,\n-      truncate_by_problem_size\n-      , bypass_occupancy_calculation \n+      truncate_by_problem_size,\n+      bypass_sm90_occupancy_calculation\n     );\n   }\n \n@@ -215,8 +215,8 @@ struct PersistentTileSchedulerSm90Params {\n     KernelHardwareInfo hw_info,\n     int max_swizzle_size,\n     RasterOrderOptions raster_order_option,\n-    bool truncate_by_problem_size=true\n-    , bool bypass_occupancy_calculation=false \n+    bool truncate_by_problem_size=true,\n+    bool bypass_sm90_occupancy_calculation=false\n     ) {\n \n     int const sm_count = hw_info.sm_count;\n@@ -267,24 +267,28 @@ struct PersistentTileSchedulerSm90Params {\n     // already calculated using cudaOccupancyMaxActiveClusters\n     else if (max_active_clusters != 0 && max_active_clusters * cluster_size <= sm_count) {\n       if (raster_order == RasterOrder::AlongN) {\n-        launch_grid.y = max_active_clusters * cluster_shape.n();\n+        launch_grid.y = possibly_truncate(\n+            max_active_clusters * cluster_shape.n(),\n+            problem_blocks_total / cluster_shape.m());\n       }\n       else {\n-        launch_grid.x = max_active_clusters * cluster_shape.m();\n+        launch_grid.x = possibly_truncate(\n+            max_active_clusters * cluster_shape.m(),\n+            problem_blocks_total / cluster_shape.n());\n       }\n       CUTLASS_TRACE_HOST(\"get_grid_shape(): Proposed GridDims by the scheduler using cudaOccupancyMaxActiveClusters = \"\n           \"(\" << launch_grid.x << \", \" << launch_grid.y << \", \" << launch_grid.z << \")\\n\");\n     }\n     else {\n       int cta_per_device = sm_count;\n-      if (!bypass_occupancy_calculation) { \n-      /*\n-      * Optimal grid size calculation is based on\n-      * GH100: 8 GPCs, 72 TPCs (9 TPCs/GPC), 2 SMs/TPC, 144 SMs per full GPU\n-      * Hence, maximum SMs per GPC = 18\n-      */\n-      constexpr int max_sm_per_gpc = 18;\n-      cta_per_device = get_max_cta_occupancy(max_sm_per_gpc, cluster_shape, sm_count);\n+      if (!bypass_sm90_occupancy_calculation) {\n+        /*\n+        * Optimal grid size calculation is based on\n+        * GH100: 8 GPCs, 72 TPCs (9 TPCs/GPC), 2 SMs/TPC, 144 SMs per full GPU\n+        * Hence, maximum SMs per GPC = 18\n+        */\n+        constexpr int max_sm_per_gpc = 18;\n+        cta_per_device = get_max_cta_occupancy(max_sm_per_gpc, cluster_shape, sm_count);\n       } \n \n       if (raster_order == RasterOrder::AlongN) {\n@@ -573,8 +577,9 @@ struct PersistentTileSchedulerSm90StreamKParams {\n     ReductionMode reduction_mode,\n     DecompositionMode decomposition_mode,\n     void* workspace,\n-    const uint32_t epilogue_subtile = 1u\n-    , uint32_t ktile_start_alignment_count = 1u \n+    const uint32_t epilogue_subtile = 1u,\n+    uint32_t ktile_start_alignment_count = 1u,\n+    bool bypass_sm90_occupancy_calculation=false\n   ) {\n     dim3 problem_blocks = UnderlyingParams::get_tiled_cta_shape_mnl(\n       problem_shape, tile_shape, cluster_shape);\n@@ -593,8 +598,9 @@ struct PersistentTileSchedulerSm90StreamKParams {\n       reduction_mode,\n       decomposition_mode,\n       workspace,\n-      epilogue_subtile\n-      , ktile_start_alignment_count \n+      epilogue_subtile,\n+      ktile_start_alignment_count,\n+      bypass_sm90_occupancy_calculation\n     );\n   }\n \n@@ -613,8 +619,9 @@ struct PersistentTileSchedulerSm90StreamKParams {\n     ReductionMode reduction_mode,\n     DecompositionMode decomposition_mode,\n     void* workspace,\n-    const uint32_t epilogue_subtile = 1\n-    , uint32_t ktile_start_alignment_count = 1u \n+    const uint32_t epilogue_subtile = 1,\n+    uint32_t ktile_start_alignment_count = 1u, \n+    bool bypass_sm90_occupancy_calculation=false\n   ) {\n \n     #if !defined(__CUDACC_RTC__)\n@@ -650,7 +657,9 @@ struct PersistentTileSchedulerSm90StreamKParams {\n       raster_order_option,\n       decomposition_mode,\n       reduction_mode,\n-      epilogue_subtile\n+      epilogue_subtile,\n+      ktile_start_alignment_count,\n+      bypass_sm90_occupancy_calculation\n     ); \n   }\n   \n@@ -741,19 +750,19 @@ struct PersistentTileSchedulerSm90StreamKParams {\n   // Stream-K kernel use below function to set stream-K feature related parameters to choose\n   // optimal/customized decomposition mode.\n   void stream_k_heuristic(\n-    UnderlyingParams underlying_params,\n-    dim3 problem_blocks,\n-    uint32_t k_tiles_per_output_tile,\n-    GemmCoord cluster_shape,\n-    KernelHardwareInfo hw_info,\n-    int splits,\n-    int max_swizzle,\n-    RasterOrderOptions raster_order_option,\n-    DecompositionMode decomposition_mode,\n-    ReductionMode reduction_mode,\n-    const uint32_t epilogue_subtile = 1\n-    , uint32_t ktile_start_alignment_count = 1u \n-    ) {\n+      UnderlyingParams underlying_params,\n+      dim3 problem_blocks,\n+      uint32_t k_tiles_per_output_tile,\n+      GemmCoord cluster_shape,\n+      KernelHardwareInfo hw_info,\n+      int splits,\n+      int max_swizzle,\n+      RasterOrderOptions raster_order_option,\n+      DecompositionMode decomposition_mode,\n+      ReductionMode reduction_mode,\n+      const uint32_t epilogue_subtile = 1,\n+      uint32_t ktile_start_alignment_count = 1u,\n+      bool bypass_sm90_occupancy_calculation=false) {\n     uint32_t groups = 0;\n     uint32_t sk_tiles = 0;\n     uint64_t sk_units = 0;\n@@ -785,8 +794,9 @@ struct PersistentTileSchedulerSm90StreamKParams {\n         raster_order_option,\n         decomposition_mode,\n         reduction_mode,\n-        epilogue_subtile\n-        , ktile_start_alignment_count \n+        epilogue_subtile,\n+        ktile_start_alignment_count,\n+        bypass_sm90_occupancy_calculation\n       );\n \n     // Given heuristic_mode returned from the heuristic() method, set params fields.\n@@ -809,8 +819,8 @@ struct PersistentTileSchedulerSm90StreamKParams {\n       cluster_shape,\n       splits,\n       epilogue_subtile,\n-      reduction_mode\n-      , ktile_start_alignment_count \n+      reduction_mode,\n+      ktile_start_alignment_count\n       );\n   }\n \n@@ -835,8 +845,9 @@ struct PersistentTileSchedulerSm90StreamKParams {\n     RasterOrderOptions raster_order_option,\n     DecompositionMode decomposition_mode,\n     ReductionMode reduction_mode,\n-    uint32_t epilogue_subtile\n-    , uint32_t ktile_start_alignment_count \n+    uint32_t epilogue_subtile,\n+    uint32_t ktile_start_alignment_count,\n+    bool bypass_sm90_occupancy_calculation=false\n   ) {\n \n     // Get block numbers in m, n and l dimensions\n@@ -863,7 +874,8 @@ struct PersistentTileSchedulerSm90StreamKParams {\n         cluster_shape,\n         hw_info,\n         max_swizzle,\n-        raster_order_option\n+        raster_order_option,\n+        bypass_sm90_occupancy_calculation\n       );\n       uint64_t ctas_per_wave = grid.x * grid.y;\n       cluster_size = cluster_shape.m() * cluster_shape.n();\n@@ -875,8 +887,8 @@ struct PersistentTileSchedulerSm90StreamKParams {\n         ctas_per_wave,\n         cluster_size,\n         k_tiles_per_output_tile,\n-        decomposition_mode\n-        , ctas_per_wave_in_full_clusters \n+        decomposition_mode,\n+        ctas_per_wave_in_full_clusters\n       );\n       uint64_t dp_tiles = output_tiles - sk_tiles;\n       // Calculate the number of work units covering the data-parallel and stream-K tiles.\n@@ -1035,7 +1047,8 @@ struct PersistentTileSchedulerSm90StreamKParams {\n     GemmCoord cluster_shape,\n     KernelHardwareInfo hw_info,\n     int max_swizzle_size,\n-    RasterOrderOptions raster_order_option\n+    RasterOrderOptions raster_order_option,\n+    bool bypass_sm90_occupancy_calculation=false\n   ) {\n \n     dim3 problem_blocks = UnderlyingParams::get_tiled_cta_shape_mnl(problem_shape, cta_shape, cluster_shape);\n@@ -1045,7 +1058,8 @@ struct PersistentTileSchedulerSm90StreamKParams {\n       cluster_shape,\n       hw_info,\n       max_swizzle_size,\n-      raster_order_option\n+      raster_order_option,\n+      bypass_sm90_occupancy_calculation\n     );\n   }\n \n@@ -1059,7 +1073,8 @@ struct PersistentTileSchedulerSm90StreamKParams {\n     GemmCoord cluster_shape,\n     KernelHardwareInfo hw_info,\n     int max_swizzle_size,\n-    RasterOrderOptions raster_order_option\n+    RasterOrderOptions raster_order_option,\n+    bool bypass_sm90_occupancy_calculation=false\n   ) {\n \n     // Call into the underlying get_grid_shape method, but do not allow the grid shape returned\n@@ -1070,8 +1085,8 @@ struct PersistentTileSchedulerSm90StreamKParams {\n       hw_info,\n       max_swizzle_size,\n       raster_order_option,\n-      /* truncate_by_problem_size = */false\n-      /* bypass_occupancy_calculation = */, true \n+      /* truncate_by_problem_size = */false,\n+      bypass_sm90_occupancy_calculation\n     );\n   }\n \n@@ -1186,7 +1201,8 @@ struct PersistentTileSchedulerSm90StreamKParams {\n     uint32_t accumulator_bits,\n     uint32_t epilogue_subtile = 1,\n     uint32_t num_accumulator_mtxs = 1,\n-    uint32_t ktile_start_alignment_count = 1) {\n+    uint32_t ktile_start_alignment_count = 1,\n+    bool bypass_sm90_occupancy_calculation=false) {\n \n     auto log_swizzle_size = UnderlyingParams::get_log_swizzle_size(problem_blocks.x, problem_blocks.y, max_swizzle);\n     problem_blocks.x = round_up(problem_blocks.x, (1 << log_swizzle_size) * cluster_shape.m());\n@@ -1216,7 +1232,8 @@ struct PersistentTileSchedulerSm90StreamKParams {\n         cluster_shape,\n         new_hw_info,\n         max_swizzle,\n-        raster_order_option\n+        raster_order_option,\n+        bypass_sm90_occupancy_calculation\n       );\n       uint64_t ctas_per_wave = grid.x * grid.y;\n       uint64_t cluster_size = cluster_shape.m() * cluster_shape.n();\n@@ -1347,7 +1364,8 @@ struct PersistentTileSchedulerSm90StreamKParams {\n     uint32_t element_accumulator_bits,\n     uint32_t epilogue_subtile = 1,\n     uint32_t num_accumulator_mtxs = 1,\n-    uint32_t ktile_start_alignment_count = 1) {\n+    uint32_t ktile_start_alignment_count = 1,\n+    bool bypass_sm90_occupancy_calculation=false) {\n \n     size_t barrier_workspace_size = 0;\n     size_t reduction_workspace_size = 0;\n@@ -1371,7 +1389,8 @@ struct PersistentTileSchedulerSm90StreamKParams {\n         element_accumulator_bits,\n         epilogue_subtile,\n         num_accumulator_mtxs,\n-        ktile_start_alignment_count\n+        ktile_start_alignment_count,\n+        bypass_sm90_occupancy_calculation\n       );\n     #endif\n \n@@ -1449,7 +1468,8 @@ struct PersistentTileSchedulerSm90StreamKParams {\n     uint32_t epilogue_subtile = 1,\n     uint32_t num_accumulator_mtxs = 1,\n     CudaHostAdapter* cuda_adapter = nullptr,\n-    uint32_t ktile_start_alignment_count = 1) {\n+    uint32_t ktile_start_alignment_count = 1,\n+    bool bypass_sm90_occupancy_calculation=false) {\n \n     #if !defined(__CUDACC_RTC__)\n       uint64_t barrier_workspace_size = 0;\n@@ -1473,7 +1493,8 @@ struct PersistentTileSchedulerSm90StreamKParams {\n         element_accumulator_bits,\n         epilogue_subtile,\n         num_accumulator_mtxs,\n-        ktile_start_alignment_count\n+        ktile_start_alignment_count,\n+        bypass_sm90_occupancy_calculation\n       );\n \n       if (barrier_workspace_size > 0) {\n@@ -2165,7 +2186,8 @@ struct PersistentTileSchedulerSm100StreamKParams {\n       decomposition_mode,\n       workspace,\n       /*epilogue_subtile=*/1,\n-      ktile_start_alignment_count\n+      ktile_start_alignment_count,\n+      /*bypass_sm90_occupancy_calculation=*/true\n     );\n \n     log_swizzle_size_ = sk_params_.log_swizzle_size_;\n@@ -2334,7 +2356,8 @@ struct PersistentTileSchedulerSm100StreamKParams {\n       element_accumulator_bits,\n       epilogue_subtile,\n       num_accumulator_mtxs,\n-      ktile_start_alignment_count\n+      ktile_start_alignment_count,\n+      /*bypass_sm90_occupancy_calculation=*/true\n     );\n   }\n \n@@ -2431,7 +2454,8 @@ struct PersistentTileSchedulerSm100StreamKParams {\n       epilogue_subtile,\n       num_accumulator_mtxs,\n       cuda_adapter,\n-      ktile_start_alignment_count\n+      ktile_start_alignment_count,\n+      /*bypass_sm90_occupancy_calculation=*/true\n     );\n   }\n };"
    }
  ]
}