{
  "pull": {
    "url": "https://api.github.com/repos/NVIDIA/cutlass/pulls/2292",
    "id": 2515525978,
    "node_id": "PR_kwDOBrVDM86V7-Fa",
    "html_url": "https://github.com/NVIDIA/cutlass/pull/2292",
    "diff_url": "https://github.com/NVIDIA/cutlass/pull/2292.diff",
    "patch_url": "https://github.com/NVIDIA/cutlass/pull/2292.patch",
    "issue_url": "https://api.github.com/repos/NVIDIA/cutlass/issues/2292",
    "number": 2292,
    "state": "closed",
    "locked": false,
    "title": "Handle get_masked_trip_count for small length in fmha example",
    "user": {
      "login": "ktaebum",
      "id": 19629048,
      "node_id": "MDQ6VXNlcjE5NjI5MDQ4",
      "avatar_url": "https://avatars.githubusercontent.com/u/19629048?v=4",
      "gravatar_id": "",
      "url": "https://api.github.com/users/ktaebum",
      "html_url": "https://github.com/ktaebum",
      "followers_url": "https://api.github.com/users/ktaebum/followers",
      "following_url": "https://api.github.com/users/ktaebum/following{/other_user}",
      "gists_url": "https://api.github.com/users/ktaebum/gists{/gist_id}",
      "starred_url": "https://api.github.com/users/ktaebum/starred{/owner}{/repo}",
      "subscriptions_url": "https://api.github.com/users/ktaebum/subscriptions",
      "organizations_url": "https://api.github.com/users/ktaebum/orgs",
      "repos_url": "https://api.github.com/users/ktaebum/repos",
      "events_url": "https://api.github.com/users/ktaebum/events{/privacy}",
      "received_events_url": "https://api.github.com/users/ktaebum/received_events",
      "type": "User",
      "user_view_type": "public",
      "site_admin": false
    },
    "body": "Current code cannot handle when trip count is smaller than `ceil_div(get<0>(tile_shape), get<1>(tile_shape))`.",
    "created_at": "2025-05-13T05:53:27Z",
    "updated_at": "2025-05-31T03:15:49Z",
    "closed_at": "2025-05-31T02:51:19Z",
    "merged_at": "2025-05-31T02:51:19Z",
    "merge_commit_sha": "9d165a3b8ef446a7ff3db198413f82bcb83f46fe",
    "assignees": [],
    "requested_reviewers": [],
    "requested_teams": [],
    "labels": [],
    "milestone": null,
    "draft": false,
    "commits_url": "https://api.github.com/repos/NVIDIA/cutlass/pulls/2292/commits",
    "review_comments_url": "https://api.github.com/repos/NVIDIA/cutlass/pulls/2292/comments",
    "review_comment_url": "https://api.github.com/repos/NVIDIA/cutlass/pulls/comments{/number}",
    "comments_url": "https://api.github.com/repos/NVIDIA/cutlass/issues/2292/comments",
    "statuses_url": "https://api.github.com/repos/NVIDIA/cutlass/statuses/a915e05f86d18eac610e24c3bdf93e9a48ff11e6",
    "head": {
      "label": "ktaebum:ex77-causal-mask-small-length",
      "ref": "ex77-causal-mask-small-length",
      "sha": "a915e05f86d18eac610e24c3bdf93e9a48ff11e6",
      "user": {
        "login": "ktaebum",
        "id": 19629048,
        "node_id": "MDQ6VXNlcjE5NjI5MDQ4",
        "avatar_url": "https://avatars.githubusercontent.com/u/19629048?v=4",
        "gravatar_id": "",
        "url": "https://api.github.com/users/ktaebum",
        "html_url": "https://github.com/ktaebum",
        "followers_url": "https://api.github.com/users/ktaebum/followers",
        "following_url": "https://api.github.com/users/ktaebum/following{/other_user}",
        "gists_url": "https://api.github.com/users/ktaebum/gists{/gist_id}",
        "starred_url": "https://api.github.com/users/ktaebum/starred{/owner}{/repo}",
        "subscriptions_url": "https://api.github.com/users/ktaebum/subscriptions",
        "organizations_url": "https://api.github.com/users/ktaebum/orgs",
        "repos_url": "https://api.github.com/users/ktaebum/repos",
        "events_url": "https://api.github.com/users/ktaebum/events{/privacy}",
        "received_events_url": "https://api.github.com/users/ktaebum/received_events",
        "type": "User",
        "user_view_type": "public",
        "site_admin": false
      },
      "repo": {
        "id": 982581218,
        "node_id": "R_kgDOOpD_4g",
        "name": "cutlass",
        "full_name": "ktaebum/cutlass",
        "private": false,
        "owner": {
          "login": "ktaebum",
          "id": 19629048,
          "node_id": "MDQ6VXNlcjE5NjI5MDQ4",
          "avatar_url": "https://avatars.githubusercontent.com/u/19629048?v=4",
          "gravatar_id": "",
          "url": "https://api.github.com/users/ktaebum",
          "html_url": "https://github.com/ktaebum",
          "followers_url": "https://api.github.com/users/ktaebum/followers",
          "following_url": "https://api.github.com/users/ktaebum/following{/other_user}",
          "gists_url": "https://api.github.com/users/ktaebum/gists{/gist_id}",
          "starred_url": "https://api.github.com/users/ktaebum/starred{/owner}{/repo}",
          "subscriptions_url": "https://api.github.com/users/ktaebum/subscriptions",
          "organizations_url": "https://api.github.com/users/ktaebum/orgs",
          "repos_url": "https://api.github.com/users/ktaebum/repos",
          "events_url": "https://api.github.com/users/ktaebum/events{/privacy}",
          "received_events_url": "https://api.github.com/users/ktaebum/received_events",
          "type": "User",
          "user_view_type": "public",
          "site_admin": false
        },
        "html_url": "https://github.com/ktaebum/cutlass",
        "description": "CUDA Templates for Linear Algebra Subroutines",
        "fork": true,
        "url": "https://api.github.com/repos/ktaebum/cutlass",
        "forks_url": "https://api.github.com/repos/ktaebum/cutlass/forks",
        "keys_url": "https://api.github.com/repos/ktaebum/cutlass/keys{/key_id}",
        "collaborators_url": "https://api.github.com/repos/ktaebum/cutlass/collaborators{/collaborator}",
        "teams_url": "https://api.github.com/repos/ktaebum/cutlass/teams",
        "hooks_url": "https://api.github.com/repos/ktaebum/cutlass/hooks",
        "issue_events_url": "https://api.github.com/repos/ktaebum/cutlass/issues/events{/number}",
        "events_url": "https://api.github.com/repos/ktaebum/cutlass/events",
        "assignees_url": "https://api.github.com/repos/ktaebum/cutlass/assignees{/user}",
        "branches_url": "https://api.github.com/repos/ktaebum/cutlass/branches{/branch}",
        "tags_url": "https://api.github.com/repos/ktaebum/cutlass/tags",
        "blobs_url": "https://api.github.com/repos/ktaebum/cutlass/git/blobs{/sha}",
        "git_tags_url": "https://api.github.com/repos/ktaebum/cutlass/git/tags{/sha}",
        "git_refs_url": "https://api.github.com/repos/ktaebum/cutlass/git/refs{/sha}",
        "trees_url": "https://api.github.com/repos/ktaebum/cutlass/git/trees{/sha}",
        "statuses_url": "https://api.github.com/repos/ktaebum/cutlass/statuses/{sha}",
        "languages_url": "https://api.github.com/repos/ktaebum/cutlass/languages",
        "stargazers_url": "https://api.github.com/repos/ktaebum/cutlass/stargazers",
        "contributors_url": "https://api.github.com/repos/ktaebum/cutlass/contributors",
        "subscribers_url": "https://api.github.com/repos/ktaebum/cutlass/subscribers",
        "subscription_url": "https://api.github.com/repos/ktaebum/cutlass/subscription",
        "commits_url": "https://api.github.com/repos/ktaebum/cutlass/commits{/sha}",
        "git_commits_url": "https://api.github.com/repos/ktaebum/cutlass/git/commits{/sha}",
        "comments_url": "https://api.github.com/repos/ktaebum/cutlass/comments{/number}",
        "issue_comment_url": "https://api.github.com/repos/ktaebum/cutlass/issues/comments{/number}",
        "contents_url": "https://api.github.com/repos/ktaebum/cutlass/contents/{+path}",
        "compare_url": "https://api.github.com/repos/ktaebum/cutlass/compare/{base}...{head}",
        "merges_url": "https://api.github.com/repos/ktaebum/cutlass/merges",
        "archive_url": "https://api.github.com/repos/ktaebum/cutlass/{archive_format}{/ref}",
        "downloads_url": "https://api.github.com/repos/ktaebum/cutlass/downloads",
        "issues_url": "https://api.github.com/repos/ktaebum/cutlass/issues{/number}",
        "pulls_url": "https://api.github.com/repos/ktaebum/cutlass/pulls{/number}",
        "milestones_url": "https://api.github.com/repos/ktaebum/cutlass/milestones{/number}",
        "notifications_url": "https://api.github.com/repos/ktaebum/cutlass/notifications{?since,all,participating}",
        "labels_url": "https://api.github.com/repos/ktaebum/cutlass/labels{/name}",
        "releases_url": "https://api.github.com/repos/ktaebum/cutlass/releases{/id}",
        "deployments_url": "https://api.github.com/repos/ktaebum/cutlass/deployments",
        "created_at": "2025-05-13T05:32:35Z",
        "updated_at": "2025-05-13T05:32:35Z",
        "pushed_at": "2025-05-31T03:15:59Z",
        "git_url": "git://github.com/ktaebum/cutlass.git",
        "ssh_url": "git@github.com:ktaebum/cutlass.git",
        "clone_url": "https://github.com/ktaebum/cutlass.git",
        "svn_url": "https://github.com/ktaebum/cutlass",
        "homepage": "",
        "size": 50718,
        "stargazers_count": 0,
        "watchers_count": 0,
        "language": null,
        "has_issues": false,
        "has_projects": true,
        "has_downloads": true,
        "has_wiki": true,
        "has_pages": false,
        "has_discussions": false,
        "forks_count": 0,
        "mirror_url": null,
        "archived": false,
        "disabled": false,
        "open_issues_count": 0,
        "license": {
          "key": "other",
          "name": "Other",
          "spdx_id": "NOASSERTION",
          "url": null,
          "node_id": "MDc6TGljZW5zZTA="
        },
        "allow_forking": true,
        "is_template": false,
        "web_commit_signoff_required": false,
        "has_pull_requests": true,
        "pull_request_creation_policy": "all",
        "topics": [],
        "visibility": "public",
        "forks": 0,
        "open_issues": 0,
        "watchers": 0,
        "default_branch": "main"
      }
    },
    "base": {
      "label": "NVIDIA:main",
      "ref": "main",
      "sha": "ad7b2f5e84fcfa124cb02b91d5bd26d238c0459e",
      "user": {
        "login": "NVIDIA",
        "id": 1728152,
        "node_id": "MDEyOk9yZ2FuaXphdGlvbjE3MjgxNTI=",
        "avatar_url": "https://avatars.githubusercontent.com/u/1728152?v=4",
        "gravatar_id": "",
        "url": "https://api.github.com/users/NVIDIA",
        "html_url": "https://github.com/NVIDIA",
        "followers_url": "https://api.github.com/users/NVIDIA/followers",
        "following_url": "https://api.github.com/users/NVIDIA/following{/other_user}",
        "gists_url": "https://api.github.com/users/NVIDIA/gists{/gist_id}",
        "starred_url": "https://api.github.com/users/NVIDIA/starred{/owner}{/repo}",
        "subscriptions_url": "https://api.github.com/users/NVIDIA/subscriptions",
        "organizations_url": "https://api.github.com/users/NVIDIA/orgs",
        "repos_url": "https://api.github.com/users/NVIDIA/repos",
        "events_url": "https://api.github.com/users/NVIDIA/events{/privacy}",
        "received_events_url": "https://api.github.com/users/NVIDIA/received_events",
        "type": "Organization",
        "user_view_type": "public",
        "site_admin": false
      },
      "repo": {
        "id": 112542515,
        "node_id": "MDEwOlJlcG9zaXRvcnkxMTI1NDI1MTU=",
        "name": "cutlass",
        "full_name": "NVIDIA/cutlass",
        "private": false,
        "owner": {
          "login": "NVIDIA",
          "id": 1728152,
          "node_id": "MDEyOk9yZ2FuaXphdGlvbjE3MjgxNTI=",
          "avatar_url": "https://avatars.githubusercontent.com/u/1728152?v=4",
          "gravatar_id": "",
          "url": "https://api.github.com/users/NVIDIA",
          "html_url": "https://github.com/NVIDIA",
          "followers_url": "https://api.github.com/users/NVIDIA/followers",
          "following_url": "https://api.github.com/users/NVIDIA/following{/other_user}",
          "gists_url": "https://api.github.com/users/NVIDIA/gists{/gist_id}",
          "starred_url": "https://api.github.com/users/NVIDIA/starred{/owner}{/repo}",
          "subscriptions_url": "https://api.github.com/users/NVIDIA/subscriptions",
          "organizations_url": "https://api.github.com/users/NVIDIA/orgs",
          "repos_url": "https://api.github.com/users/NVIDIA/repos",
          "events_url": "https://api.github.com/users/NVIDIA/events{/privacy}",
          "received_events_url": "https://api.github.com/users/NVIDIA/received_events",
          "type": "Organization",
          "user_view_type": "public",
          "site_admin": false
        },
        "html_url": "https://github.com/NVIDIA/cutlass",
        "description": "CUDA Templates and Python DSLs for High-Performance Linear Algebra",
        "fork": false,
        "url": "https://api.github.com/repos/NVIDIA/cutlass",
        "forks_url": "https://api.github.com/repos/NVIDIA/cutlass/forks",
        "keys_url": "https://api.github.com/repos/NVIDIA/cutlass/keys{/key_id}",
        "collaborators_url": "https://api.github.com/repos/NVIDIA/cutlass/collaborators{/collaborator}",
        "teams_url": "https://api.github.com/repos/NVIDIA/cutlass/teams",
        "hooks_url": "https://api.github.com/repos/NVIDIA/cutlass/hooks",
        "issue_events_url": "https://api.github.com/repos/NVIDIA/cutlass/issues/events{/number}",
        "events_url": "https://api.github.com/repos/NVIDIA/cutlass/events",
        "assignees_url": "https://api.github.com/repos/NVIDIA/cutlass/assignees{/user}",
        "branches_url": "https://api.github.com/repos/NVIDIA/cutlass/branches{/branch}",
        "tags_url": "https://api.github.com/repos/NVIDIA/cutlass/tags",
        "blobs_url": "https://api.github.com/repos/NVIDIA/cutlass/git/blobs{/sha}",
        "git_tags_url": "https://api.github.com/repos/NVIDIA/cutlass/git/tags{/sha}",
        "git_refs_url": "https://api.github.com/repos/NVIDIA/cutlass/git/refs{/sha}",
        "trees_url": "https://api.github.com/repos/NVIDIA/cutlass/git/trees{/sha}",
        "statuses_url": "https://api.github.com/repos/NVIDIA/cutlass/statuses/{sha}",
        "languages_url": "https://api.github.com/repos/NVIDIA/cutlass/languages",
        "stargazers_url": "https://api.github.com/repos/NVIDIA/cutlass/stargazers",
        "contributors_url": "https://api.github.com/repos/NVIDIA/cutlass/contributors",
        "subscribers_url": "https://api.github.com/repos/NVIDIA/cutlass/subscribers",
        "subscription_url": "https://api.github.com/repos/NVIDIA/cutlass/subscription",
        "commits_url": "https://api.github.com/repos/NVIDIA/cutlass/commits{/sha}",
        "git_commits_url": "https://api.github.com/repos/NVIDIA/cutlass/git/commits{/sha}",
        "comments_url": "https://api.github.com/repos/NVIDIA/cutlass/comments{/number}",
        "issue_comment_url": "https://api.github.com/repos/NVIDIA/cutlass/issues/comments{/number}",
        "contents_url": "https://api.github.com/repos/NVIDIA/cutlass/contents/{+path}",
        "compare_url": "https://api.github.com/repos/NVIDIA/cutlass/compare/{base}...{head}",
        "merges_url": "https://api.github.com/repos/NVIDIA/cutlass/merges",
        "archive_url": "https://api.github.com/repos/NVIDIA/cutlass/{archive_format}{/ref}",
        "downloads_url": "https://api.github.com/repos/NVIDIA/cutlass/downloads",
        "issues_url": "https://api.github.com/repos/NVIDIA/cutlass/issues{/number}",
        "pulls_url": "https://api.github.com/repos/NVIDIA/cutlass/pulls{/number}",
        "milestones_url": "https://api.github.com/repos/NVIDIA/cutlass/milestones{/number}",
        "notifications_url": "https://api.github.com/repos/NVIDIA/cutlass/notifications{?since,all,participating}",
        "labels_url": "https://api.github.com/repos/NVIDIA/cutlass/labels{/name}",
        "releases_url": "https://api.github.com/repos/NVIDIA/cutlass/releases{/id}",
        "deployments_url": "https://api.github.com/repos/NVIDIA/cutlass/deployments",
        "created_at": "2017-11-30T00:11:24Z",
        "updated_at": "2026-05-15T21:07:57Z",
        "pushed_at": "2026-05-13T03:39:02Z",
        "git_url": "git://github.com/NVIDIA/cutlass.git",
        "ssh_url": "git@github.com:NVIDIA/cutlass.git",
        "clone_url": "https://github.com/NVIDIA/cutlass.git",
        "svn_url": "https://github.com/NVIDIA/cutlass",
        "homepage": "https://docs.nvidia.com/cutlass/index.html",
        "size": 67022,
        "stargazers_count": 9728,
        "watchers_count": 9728,
        "language": "C++",
        "has_issues": true,
        "has_projects": true,
        "has_downloads": true,
        "has_wiki": true,
        "has_pages": true,
        "has_discussions": true,
        "forks_count": 1855,
        "mirror_url": null,
        "archived": false,
        "disabled": false,
        "open_issues_count": 640,
        "license": {
          "key": "other",
          "name": "Other",
          "spdx_id": "NOASSERTION",
          "url": null,
          "node_id": "MDc6TGljZW5zZTA="
        },
        "allow_forking": true,
        "is_template": false,
        "web_commit_signoff_required": false,
        "has_pull_requests": true,
        "pull_request_creation_policy": "all",
        "topics": [
          "cpp",
          "cuda",
          "deep-learning",
          "deep-learning-library",
          "gpu",
          "nvidia",
          "python"
        ],
        "visibility": "public",
        "forks": 1855,
        "open_issues": 640,
        "watchers": 9728,
        "default_branch": "main"
      }
    },
    "_links": {
      "self": {
        "href": "https://api.github.com/repos/NVIDIA/cutlass/pulls/2292"
      },
      "html": {
        "href": "https://github.com/NVIDIA/cutlass/pull/2292"
      },
      "issue": {
        "href": "https://api.github.com/repos/NVIDIA/cutlass/issues/2292"
      },
      "comments": {
        "href": "https://api.github.com/repos/NVIDIA/cutlass/issues/2292/comments"
      },
      "review_comments": {
        "href": "https://api.github.com/repos/NVIDIA/cutlass/pulls/2292/comments"
      },
      "review_comment": {
        "href": "https://api.github.com/repos/NVIDIA/cutlass/pulls/comments{/number}"
      },
      "commits": {
        "href": "https://api.github.com/repos/NVIDIA/cutlass/pulls/2292/commits"
      },
      "statuses": {
        "href": "https://api.github.com/repos/NVIDIA/cutlass/statuses/a915e05f86d18eac610e24c3bdf93e9a48ff11e6"
      }
    },
    "author_association": "CONTRIBUTOR",
    "auto_merge": null,
    "assignee": null,
    "active_lock_reason": null,
    "merged": true,
    "mergeable": null,
    "rebaseable": null,
    "mergeable_state": "unknown",
    "merged_by": {
      "login": "hwu36",
      "id": 57973641,
      "node_id": "MDQ6VXNlcjU3OTczNjQx",
      "avatar_url": "https://avatars.githubusercontent.com/u/57973641?v=4",
      "gravatar_id": "",
      "url": "https://api.github.com/users/hwu36",
      "html_url": "https://github.com/hwu36",
      "followers_url": "https://api.github.com/users/hwu36/followers",
      "following_url": "https://api.github.com/users/hwu36/following{/other_user}",
      "gists_url": "https://api.github.com/users/hwu36/gists{/gist_id}",
      "starred_url": "https://api.github.com/users/hwu36/starred{/owner}{/repo}",
      "subscriptions_url": "https://api.github.com/users/hwu36/subscriptions",
      "organizations_url": "https://api.github.com/users/hwu36/orgs",
      "repos_url": "https://api.github.com/users/hwu36/repos",
      "events_url": "https://api.github.com/users/hwu36/events{/privacy}",
      "received_events_url": "https://api.github.com/users/hwu36/received_events",
      "type": "User",
      "user_view_type": "public",
      "site_admin": false
    },
    "comments": 4,
    "review_comments": 5,
    "maintainer_can_modify": false,
    "commits": 3,
    "additions": 2,
    "deletions": 1,
    "changed_files": 1
  },
  "files": [
    {
      "sha": "f31c8024bd2a4481a777d6a21364e15c28d1bb19",
      "filename": "examples/77_blackwell_fmha/collective/fmha_fusion.hpp",
      "status": "modified",
      "additions": 2,
      "deletions": 1,
      "changes": 3,
      "blob_url": "https://github.com/NVIDIA/cutlass/blob/a915e05f86d18eac610e24c3bdf93e9a48ff11e6/examples%2F77_blackwell_fmha%2Fcollective%2Ffmha_fusion.hpp",
      "raw_url": "https://github.com/NVIDIA/cutlass/raw/a915e05f86d18eac610e24c3bdf93e9a48ff11e6/examples%2F77_blackwell_fmha%2Fcollective%2Ffmha_fusion.hpp",
      "contents_url": "https://api.github.com/repos/NVIDIA/cutlass/contents/examples%2F77_blackwell_fmha%2Fcollective%2Ffmha_fusion.hpp?ref=a915e05f86d18eac610e24c3bdf93e9a48ff11e6",
      "patch": "@@ -157,7 +157,8 @@ struct CausalMask : NoMask {\n       TileShape const& tile_shape,\n       ProblemSize const& problem_size) {\n \n-    return ceil_div(get<0>(tile_shape), get<1>(tile_shape));\n+    int trip_count = get_trip_count(blk_coord, tile_shape, problem_size);\n+    return std::min(trip_count, int(ceil_div(size<0>(tile_shape), size<1>(tile_shape))));\n   }\n \n   template<class BlkCoord, class TileShape, class ProblemSize>"
    }
  ],
  "source_page": "sources/prs/cutlass/PR-2292.md"
}