{
  "pull": {
    "url": "https://api.github.com/repos/pytorch/pytorch/pulls/163388",
    "id": 2845518132,
    "node_id": "PR_kwDOA-j9z86pmyk0",
    "html_url": "https://github.com/pytorch/pytorch/pull/163388",
    "diff_url": "https://github.com/pytorch/pytorch/pull/163388.diff",
    "patch_url": "https://github.com/pytorch/pytorch/pull/163388.patch",
    "issue_url": "https://api.github.com/repos/pytorch/pytorch/issues/163388",
    "number": 163388,
    "state": "closed",
    "locked": false,
    "title": "[Inductor][Intel GPU] Save `threads_per_warp` from tirton compiled kernel for launching kernel correctly in cpp wrapper.",
    "user": {
      "login": "pytorchbot",
      "id": 21957446,
      "node_id": "MDQ6VXNlcjIxOTU3NDQ2",
      "avatar_url": "https://avatars.githubusercontent.com/u/21957446?v=4",
      "gravatar_id": "",
      "url": "https://api.github.com/users/pytorchbot",
      "html_url": "https://github.com/pytorchbot",
      "followers_url": "https://api.github.com/users/pytorchbot/followers",
      "following_url": "https://api.github.com/users/pytorchbot/following{/other_user}",
      "gists_url": "https://api.github.com/users/pytorchbot/gists{/gist_id}",
      "starred_url": "https://api.github.com/users/pytorchbot/starred{/owner}{/repo}",
      "subscriptions_url": "https://api.github.com/users/pytorchbot/subscriptions",
      "organizations_url": "https://api.github.com/users/pytorchbot/orgs",
      "repos_url": "https://api.github.com/users/pytorchbot/repos",
      "events_url": "https://api.github.com/users/pytorchbot/events{/privacy}",
      "received_events_url": "https://api.github.com/users/pytorchbot/received_events",
      "type": "User",
      "user_view_type": "public",
      "site_admin": false
    },
    "body": "Stack from [ghstack](https://github.com/ezyang/ghstack) (oldest at bottom):\n* __->__ #163315\n\r\nOn the Inductor XPU backend, `threads_per_warp` is not always 32. For Intel GEMM Triton kernels, it can be 16. This information must be preserved for XPU so that the Cpp wrapper can launch the kernel with the correct configuration.\r\n \r\n\r\ncc @voznesenskym @penguinwu @EikanWang @jgong5 @Guobing-Chen @XiaobingSuper @zhuhaozhe @blzheng @wenzhe-nrv @jiayisunx @ipiszy @chenyang78 @kadeng @muchulee8 @amjames @chauhang @aakhundov @coconutruben",
    "created_at": "2025-09-20T00:02:49Z",
    "updated_at": "2025-10-27T02:19:18Z",
    "closed_at": "2025-09-26T18:42:09Z",
    "merged_at": "2025-09-26T18:42:09Z",
    "merge_commit_sha": "7cadf8ac046a09e862b1e5b8ba50be81decab377",
    "assignees": [],
    "requested_reviewers": [],
    "requested_teams": [],
    "labels": [
      {
        "id": 1392590051,
        "node_id": "MDU6TGFiZWwxMzkyNTkwMDUx",
        "url": "https://api.github.com/repos/pytorch/pytorch/labels/open%20source",
        "name": "open source",
        "color": "ededed",
        "default": false,
        "description": null
      },
      {
        "id": 4631339377,
        "node_id": "LA_kwDOA-j9z88AAAABFAyhcQ",
        "url": "https://api.github.com/repos/pytorch/pytorch/labels/module:%20inductor",
        "name": "module: inductor",
        "color": "f9d0c4",
        "default": false,
        "description": ""
      },
      {
        "id": 4668973195,
        "node_id": "LA_kwDOA-j9z88AAAABFkrgiw",
        "url": "https://api.github.com/repos/pytorch/pytorch/labels/ciflow/inductor",
        "name": "ciflow/inductor",
        "color": "8E9C02",
        "default": false,
        "description": ""
      },
      {
        "id": 6344851958,
        "node_id": "LA_kwDOA-j9z88AAAABei7B9g",
        "url": "https://api.github.com/repos/pytorch/pytorch/labels/ciflow/xpu",
        "name": "ciflow/xpu",
        "color": "0091FF",
        "default": false,
        "description": "Run XPU CI tasks"
      },
      {
        "id": 8468702836,
        "node_id": "LA_kwDOA-j9z88AAAAB-MYmdA",
        "url": "https://api.github.com/repos/pytorch/pytorch/labels/release%20notes:%20inductor%20(aoti)",
        "name": "release notes: inductor (aoti)",
        "color": "d93f0b",
        "default": false,
        "description": ""
      }
    ],
    "milestone": null,
    "draft": false,
    "commits_url": "https://api.github.com/repos/pytorch/pytorch/pulls/163388/commits",
    "review_comments_url": "https://api.github.com/repos/pytorch/pytorch/pulls/163388/comments",
    "review_comment_url": "https://api.github.com/repos/pytorch/pytorch/pulls/comments{/number}",
    "comments_url": "https://api.github.com/repos/pytorch/pytorch/issues/163388/comments",
    "statuses_url": "https://api.github.com/repos/pytorch/pytorch/statuses/1f213fa7400fdb76e7ff3d4c6809b826f09c88c0",
    "head": {
      "label": "pytorch:cherry-pick-163315-by-pytorch_bot_bot_",
      "ref": "cherry-pick-163315-by-pytorch_bot_bot_",
      "sha": "1f213fa7400fdb76e7ff3d4c6809b826f09c88c0",
      "user": {
        "login": "pytorch",
        "id": 21003710,
        "node_id": "MDEyOk9yZ2FuaXphdGlvbjIxMDAzNzEw",
        "avatar_url": "https://avatars.githubusercontent.com/u/21003710?v=4",
        "gravatar_id": "",
        "url": "https://api.github.com/users/pytorch",
        "html_url": "https://github.com/pytorch",
        "followers_url": "https://api.github.com/users/pytorch/followers",
        "following_url": "https://api.github.com/users/pytorch/following{/other_user}",
        "gists_url": "https://api.github.com/users/pytorch/gists{/gist_id}",
        "starred_url": "https://api.github.com/users/pytorch/starred{/owner}{/repo}",
        "subscriptions_url": "https://api.github.com/users/pytorch/subscriptions",
        "organizations_url": "https://api.github.com/users/pytorch/orgs",
        "repos_url": "https://api.github.com/users/pytorch/repos",
        "events_url": "https://api.github.com/users/pytorch/events{/privacy}",
        "received_events_url": "https://api.github.com/users/pytorch/received_events",
        "type": "Organization",
        "user_view_type": "public",
        "site_admin": false
      },
      "repo": {
        "id": 65600975,
        "node_id": "MDEwOlJlcG9zaXRvcnk2NTYwMDk3NQ==",
        "name": "pytorch",
        "full_name": "pytorch/pytorch",
        "private": false,
        "owner": {
          "login": "pytorch",
          "id": 21003710,
          "node_id": "MDEyOk9yZ2FuaXphdGlvbjIxMDAzNzEw",
          "avatar_url": "https://avatars.githubusercontent.com/u/21003710?v=4",
          "gravatar_id": "",
          "url": "https://api.github.com/users/pytorch",
          "html_url": "https://github.com/pytorch",
          "followers_url": "https://api.github.com/users/pytorch/followers",
          "following_url": "https://api.github.com/users/pytorch/following{/other_user}",
          "gists_url": "https://api.github.com/users/pytorch/gists{/gist_id}",
          "starred_url": "https://api.github.com/users/pytorch/starred{/owner}{/repo}",
          "subscriptions_url": "https://api.github.com/users/pytorch/subscriptions",
          "organizations_url": "https://api.github.com/users/pytorch/orgs",
          "repos_url": "https://api.github.com/users/pytorch/repos",
          "events_url": "https://api.github.com/users/pytorch/events{/privacy}",
          "received_events_url": "https://api.github.com/users/pytorch/received_events",
          "type": "Organization",
          "user_view_type": "public",
          "site_admin": false
        },
        "html_url": "https://github.com/pytorch/pytorch",
        "description": "Tensors and Dynamic neural networks in Python with strong GPU acceleration",
        "fork": false,
        "url": "https://api.github.com/repos/pytorch/pytorch",
        "forks_url": "https://api.github.com/repos/pytorch/pytorch/forks",
        "keys_url": "https://api.github.com/repos/pytorch/pytorch/keys{/key_id}",
        "collaborators_url": "https://api.github.com/repos/pytorch/pytorch/collaborators{/collaborator}",
        "teams_url": "https://api.github.com/repos/pytorch/pytorch/teams",
        "hooks_url": "https://api.github.com/repos/pytorch/pytorch/hooks",
        "issue_events_url": "https://api.github.com/repos/pytorch/pytorch/issues/events{/number}",
        "events_url": "https://api.github.com/repos/pytorch/pytorch/events",
        "assignees_url": "https://api.github.com/repos/pytorch/pytorch/assignees{/user}",
        "branches_url": "https://api.github.com/repos/pytorch/pytorch/branches{/branch}",
        "tags_url": "https://api.github.com/repos/pytorch/pytorch/tags",
        "blobs_url": "https://api.github.com/repos/pytorch/pytorch/git/blobs{/sha}",
        "git_tags_url": "https://api.github.com/repos/pytorch/pytorch/git/tags{/sha}",
        "git_refs_url": "https://api.github.com/repos/pytorch/pytorch/git/refs{/sha}",
        "trees_url": "https://api.github.com/repos/pytorch/pytorch/git/trees{/sha}",
        "statuses_url": "https://api.github.com/repos/pytorch/pytorch/statuses/{sha}",
        "languages_url": "https://api.github.com/repos/pytorch/pytorch/languages",
        "stargazers_url": "https://api.github.com/repos/pytorch/pytorch/stargazers",
        "contributors_url": "https://api.github.com/repos/pytorch/pytorch/contributors",
        "subscribers_url": "https://api.github.com/repos/pytorch/pytorch/subscribers",
        "subscription_url": "https://api.github.com/repos/pytorch/pytorch/subscription",
        "commits_url": "https://api.github.com/repos/pytorch/pytorch/commits{/sha}",
        "git_commits_url": "https://api.github.com/repos/pytorch/pytorch/git/commits{/sha}",
        "comments_url": "https://api.github.com/repos/pytorch/pytorch/comments{/number}",
        "issue_comment_url": "https://api.github.com/repos/pytorch/pytorch/issues/comments{/number}",
        "contents_url": "https://api.github.com/repos/pytorch/pytorch/contents/{+path}",
        "compare_url": "https://api.github.com/repos/pytorch/pytorch/compare/{base}...{head}",
        "merges_url": "https://api.github.com/repos/pytorch/pytorch/merges",
        "archive_url": "https://api.github.com/repos/pytorch/pytorch/{archive_format}{/ref}",
        "downloads_url": "https://api.github.com/repos/pytorch/pytorch/downloads",
        "issues_url": "https://api.github.com/repos/pytorch/pytorch/issues{/number}",
        "pulls_url": "https://api.github.com/repos/pytorch/pytorch/pulls{/number}",
        "milestones_url": "https://api.github.com/repos/pytorch/pytorch/milestones{/number}",
        "notifications_url": "https://api.github.com/repos/pytorch/pytorch/notifications{?since,all,participating}",
        "labels_url": "https://api.github.com/repos/pytorch/pytorch/labels{/name}",
        "releases_url": "https://api.github.com/repos/pytorch/pytorch/releases{/id}",
        "deployments_url": "https://api.github.com/repos/pytorch/pytorch/deployments",
        "created_at": "2016-08-13T05:26:41Z",
        "updated_at": "2026-05-16T04:53:52Z",
        "pushed_at": "2026-05-16T04:53:42Z",
        "git_url": "git://github.com/pytorch/pytorch.git",
        "ssh_url": "org-21003710@github.com:pytorch/pytorch.git",
        "clone_url": "https://github.com/pytorch/pytorch.git",
        "svn_url": "https://github.com/pytorch/pytorch",
        "homepage": "https://pytorch.org",
        "size": 1337540,
        "stargazers_count": 99943,
        "watchers_count": 99943,
        "language": "Python",
        "has_issues": true,
        "has_projects": true,
        "has_downloads": true,
        "has_wiki": true,
        "has_pages": false,
        "has_discussions": false,
        "forks_count": 27801,
        "mirror_url": null,
        "archived": false,
        "disabled": false,
        "open_issues_count": 18508,
        "license": {
          "key": "other",
          "name": "Other",
          "spdx_id": "NOASSERTION",
          "url": null,
          "node_id": "MDc6TGljZW5zZTA="
        },
        "allow_forking": true,
        "is_template": false,
        "web_commit_signoff_required": false,
        "has_pull_requests": true,
        "pull_request_creation_policy": "all",
        "topics": [
          "autograd",
          "deep-learning",
          "gpu",
          "machine-learning",
          "neural-network",
          "numpy",
          "python",
          "tensor"
        ],
        "visibility": "public",
        "forks": 27801,
        "open_issues": 18508,
        "watchers": 99943,
        "default_branch": "main"
      }
    },
    "base": {
      "label": "pytorch:release/2.9",
      "ref": "release/2.9",
      "sha": "35c55da80593026e59941d9720e5101f2655cf4e",
      "user": {
        "login": "pytorch",
        "id": 21003710,
        "node_id": "MDEyOk9yZ2FuaXphdGlvbjIxMDAzNzEw",
        "avatar_url": "https://avatars.githubusercontent.com/u/21003710?v=4",
        "gravatar_id": "",
        "url": "https://api.github.com/users/pytorch",
        "html_url": "https://github.com/pytorch",
        "followers_url": "https://api.github.com/users/pytorch/followers",
        "following_url": "https://api.github.com/users/pytorch/following{/other_user}",
        "gists_url": "https://api.github.com/users/pytorch/gists{/gist_id}",
        "starred_url": "https://api.github.com/users/pytorch/starred{/owner}{/repo}",
        "subscriptions_url": "https://api.github.com/users/pytorch/subscriptions",
        "organizations_url": "https://api.github.com/users/pytorch/orgs",
        "repos_url": "https://api.github.com/users/pytorch/repos",
        "events_url": "https://api.github.com/users/pytorch/events{/privacy}",
        "received_events_url": "https://api.github.com/users/pytorch/received_events",
        "type": "Organization",
        "user_view_type": "public",
        "site_admin": false
      },
      "repo": {
        "id": 65600975,
        "node_id": "MDEwOlJlcG9zaXRvcnk2NTYwMDk3NQ==",
        "name": "pytorch",
        "full_name": "pytorch/pytorch",
        "private": false,
        "owner": {
          "login": "pytorch",
          "id": 21003710,
          "node_id": "MDEyOk9yZ2FuaXphdGlvbjIxMDAzNzEw",
          "avatar_url": "https://avatars.githubusercontent.com/u/21003710?v=4",
          "gravatar_id": "",
          "url": "https://api.github.com/users/pytorch",
          "html_url": "https://github.com/pytorch",
          "followers_url": "https://api.github.com/users/pytorch/followers",
          "following_url": "https://api.github.com/users/pytorch/following{/other_user}",
          "gists_url": "https://api.github.com/users/pytorch/gists{/gist_id}",
          "starred_url": "https://api.github.com/users/pytorch/starred{/owner}{/repo}",
          "subscriptions_url": "https://api.github.com/users/pytorch/subscriptions",
          "organizations_url": "https://api.github.com/users/pytorch/orgs",
          "repos_url": "https://api.github.com/users/pytorch/repos",
          "events_url": "https://api.github.com/users/pytorch/events{/privacy}",
          "received_events_url": "https://api.github.com/users/pytorch/received_events",
          "type": "Organization",
          "user_view_type": "public",
          "site_admin": false
        },
        "html_url": "https://github.com/pytorch/pytorch",
        "description": "Tensors and Dynamic neural networks in Python with strong GPU acceleration",
        "fork": false,
        "url": "https://api.github.com/repos/pytorch/pytorch",
        "forks_url": "https://api.github.com/repos/pytorch/pytorch/forks",
        "keys_url": "https://api.github.com/repos/pytorch/pytorch/keys{/key_id}",
        "collaborators_url": "https://api.github.com/repos/pytorch/pytorch/collaborators{/collaborator}",
        "teams_url": "https://api.github.com/repos/pytorch/pytorch/teams",
        "hooks_url": "https://api.github.com/repos/pytorch/pytorch/hooks",
        "issue_events_url": "https://api.github.com/repos/pytorch/pytorch/issues/events{/number}",
        "events_url": "https://api.github.com/repos/pytorch/pytorch/events",
        "assignees_url": "https://api.github.com/repos/pytorch/pytorch/assignees{/user}",
        "branches_url": "https://api.github.com/repos/pytorch/pytorch/branches{/branch}",
        "tags_url": "https://api.github.com/repos/pytorch/pytorch/tags",
        "blobs_url": "https://api.github.com/repos/pytorch/pytorch/git/blobs{/sha}",
        "git_tags_url": "https://api.github.com/repos/pytorch/pytorch/git/tags{/sha}",
        "git_refs_url": "https://api.github.com/repos/pytorch/pytorch/git/refs{/sha}",
        "trees_url": "https://api.github.com/repos/pytorch/pytorch/git/trees{/sha}",
        "statuses_url": "https://api.github.com/repos/pytorch/pytorch/statuses/{sha}",
        "languages_url": "https://api.github.com/repos/pytorch/pytorch/languages",
        "stargazers_url": "https://api.github.com/repos/pytorch/pytorch/stargazers",
        "contributors_url": "https://api.github.com/repos/pytorch/pytorch/contributors",
        "subscribers_url": "https://api.github.com/repos/pytorch/pytorch/subscribers",
        "subscription_url": "https://api.github.com/repos/pytorch/pytorch/subscription",
        "commits_url": "https://api.github.com/repos/pytorch/pytorch/commits{/sha}",
        "git_commits_url": "https://api.github.com/repos/pytorch/pytorch/git/commits{/sha}",
        "comments_url": "https://api.github.com/repos/pytorch/pytorch/comments{/number}",
        "issue_comment_url": "https://api.github.com/repos/pytorch/pytorch/issues/comments{/number}",
        "contents_url": "https://api.github.com/repos/pytorch/pytorch/contents/{+path}",
        "compare_url": "https://api.github.com/repos/pytorch/pytorch/compare/{base}...{head}",
        "merges_url": "https://api.github.com/repos/pytorch/pytorch/merges",
        "archive_url": "https://api.github.com/repos/pytorch/pytorch/{archive_format}{/ref}",
        "downloads_url": "https://api.github.com/repos/pytorch/pytorch/downloads",
        "issues_url": "https://api.github.com/repos/pytorch/pytorch/issues{/number}",
        "pulls_url": "https://api.github.com/repos/pytorch/pytorch/pulls{/number}",
        "milestones_url": "https://api.github.com/repos/pytorch/pytorch/milestones{/number}",
        "notifications_url": "https://api.github.com/repos/pytorch/pytorch/notifications{?since,all,participating}",
        "labels_url": "https://api.github.com/repos/pytorch/pytorch/labels{/name}",
        "releases_url": "https://api.github.com/repos/pytorch/pytorch/releases{/id}",
        "deployments_url": "https://api.github.com/repos/pytorch/pytorch/deployments",
        "created_at": "2016-08-13T05:26:41Z",
        "updated_at": "2026-05-16T04:53:52Z",
        "pushed_at": "2026-05-16T04:53:42Z",
        "git_url": "git://github.com/pytorch/pytorch.git",
        "ssh_url": "org-21003710@github.com:pytorch/pytorch.git",
        "clone_url": "https://github.com/pytorch/pytorch.git",
        "svn_url": "https://github.com/pytorch/pytorch",
        "homepage": "https://pytorch.org",
        "size": 1337540,
        "stargazers_count": 99943,
        "watchers_count": 99943,
        "language": "Python",
        "has_issues": true,
        "has_projects": true,
        "has_downloads": true,
        "has_wiki": true,
        "has_pages": false,
        "has_discussions": false,
        "forks_count": 27801,
        "mirror_url": null,
        "archived": false,
        "disabled": false,
        "open_issues_count": 18508,
        "license": {
          "key": "other",
          "name": "Other",
          "spdx_id": "NOASSERTION",
          "url": null,
          "node_id": "MDc6TGljZW5zZTA="
        },
        "allow_forking": true,
        "is_template": false,
        "web_commit_signoff_required": false,
        "has_pull_requests": true,
        "pull_request_creation_policy": "all",
        "topics": [
          "autograd",
          "deep-learning",
          "gpu",
          "machine-learning",
          "neural-network",
          "numpy",
          "python",
          "tensor"
        ],
        "visibility": "public",
        "forks": 27801,
        "open_issues": 18508,
        "watchers": 99943,
        "default_branch": "main"
      }
    },
    "_links": {
      "self": {
        "href": "https://api.github.com/repos/pytorch/pytorch/pulls/163388"
      },
      "html": {
        "href": "https://github.com/pytorch/pytorch/pull/163388"
      },
      "issue": {
        "href": "https://api.github.com/repos/pytorch/pytorch/issues/163388"
      },
      "comments": {
        "href": "https://api.github.com/repos/pytorch/pytorch/issues/163388/comments"
      },
      "review_comments": {
        "href": "https://api.github.com/repos/pytorch/pytorch/pulls/163388/comments"
      },
      "review_comment": {
        "href": "https://api.github.com/repos/pytorch/pytorch/pulls/comments{/number}"
      },
      "commits": {
        "href": "https://api.github.com/repos/pytorch/pytorch/pulls/163388/commits"
      },
      "statuses": {
        "href": "https://api.github.com/repos/pytorch/pytorch/statuses/1f213fa7400fdb76e7ff3d4c6809b826f09c88c0"
      }
    },
    "author_association": "COLLABORATOR",
    "auto_merge": null,
    "assignee": null,
    "active_lock_reason": null,
    "merged": true,
    "mergeable": null,
    "rebaseable": null,
    "mergeable_state": "unknown",
    "merged_by": {
      "login": "atalman",
      "id": 7563158,
      "node_id": "MDQ6VXNlcjc1NjMxNTg=",
      "avatar_url": "https://avatars.githubusercontent.com/u/7563158?v=4",
      "gravatar_id": "",
      "url": "https://api.github.com/users/atalman",
      "html_url": "https://github.com/atalman",
      "followers_url": "https://api.github.com/users/atalman/followers",
      "following_url": "https://api.github.com/users/atalman/following{/other_user}",
      "gists_url": "https://api.github.com/users/atalman/gists{/gist_id}",
      "starred_url": "https://api.github.com/users/atalman/starred{/owner}{/repo}",
      "subscriptions_url": "https://api.github.com/users/atalman/subscriptions",
      "organizations_url": "https://api.github.com/users/atalman/orgs",
      "repos_url": "https://api.github.com/users/atalman/repos",
      "events_url": "https://api.github.com/users/atalman/events{/privacy}",
      "received_events_url": "https://api.github.com/users/atalman/received_events",
      "type": "User",
      "user_view_type": "public",
      "site_admin": false
    },
    "comments": 2,
    "review_comments": 0,
    "maintainer_can_modify": false,
    "commits": 1,
    "additions": 13,
    "deletions": 4,
    "changed_files": 3
  },
  "files": [
    {
      "sha": "24b87fa8fa490eb6635929514dfd84344fdf41e3",
      "filename": "torch/_inductor/codegen/cpp_wrapper_gpu.py",
      "status": "modified",
      "additions": 2,
      "deletions": 0,
      "changes": 2,
      "blob_url": "https://github.com/pytorch/pytorch/blob/1f213fa7400fdb76e7ff3d4c6809b826f09c88c0/torch%2F_inductor%2Fcodegen%2Fcpp_wrapper_gpu.py",
      "raw_url": "https://github.com/pytorch/pytorch/raw/1f213fa7400fdb76e7ff3d4c6809b826f09c88c0/torch%2F_inductor%2Fcodegen%2Fcpp_wrapper_gpu.py",
      "contents_url": "https://api.github.com/repos/pytorch/pytorch/contents/torch%2F_inductor%2Fcodegen%2Fcpp_wrapper_gpu.py?ref=1f213fa7400fdb76e7ff3d4c6809b826f09c88c0",
      "patch": "@@ -234,6 +234,8 @@ def generate_launch_kernel(self, prefix, wrapper, kernel_var_name, params):\n             \"kernel_args_\",\n             \"stream_\",\n         ]\n+        if wrapper.device == \"xpu\":\n+            launch_kernel_args.append(str(params[\"threads_per_warp\"]))\n         prefix.writeline(f\"launchKernel({', '.join(launch_kernel_args)});\")\n \n "
    },
    {
      "sha": "547fad52224650efeab3858291d44b9e40ea7b61",
      "filename": "torch/_inductor/runtime/triton_heuristics.py",
      "status": "modified",
      "additions": 9,
      "deletions": 0,
      "changes": 9,
      "blob_url": "https://github.com/pytorch/pytorch/blob/1f213fa7400fdb76e7ff3d4c6809b826f09c88c0/torch%2F_inductor%2Fruntime%2Ftriton_heuristics.py",
      "raw_url": "https://github.com/pytorch/pytorch/raw/1f213fa7400fdb76e7ff3d4c6809b826f09c88c0/torch%2F_inductor%2Fruntime%2Ftriton_heuristics.py",
      "contents_url": "https://api.github.com/repos/pytorch/pytorch/contents/torch%2F_inductor%2Fruntime%2Ftriton_heuristics.py?ref=1f213fa7400fdb76e7ff3d4c6809b826f09c88c0",
      "patch": "@@ -1100,6 +1100,15 @@ def save_gpu_kernel(self, stream, launcher):\n             \"global_scratch\": launcher.global_scratch,\n             \"profile_scratch\": launcher.profile_scratch,\n         }\n+        if self.device_props.type == \"xpu\":\n+            # On the XPU backend, threads_per_warp is not always 32.\n+            # For Intel GEMM Triton kernels, it can be 16.\n+            # This information must be preserved so that the Cpp wrapper\n+            # can launch the kernel with the correct configuration.\n+            params[\"threads_per_warp\"] = getattr(\n+                launcher.bin.metadata, \"threads_per_warp\", 32\n+            )\n+\n         from torch._inductor.codecache import CudaKernelParamCache\n \n         bin_type = {\"hip\": \"hsaco\", \"xpu\": \"spv\"}.get(self.device_props.type, \"cubin\")"
    },
    {
      "sha": "3a2e91c37c9161320698de0ae5d3fbdf078968c4",
      "filename": "torch/csrc/inductor/aoti_runtime/sycl_runtime_wrappers.h",
      "status": "modified",
      "additions": 2,
      "deletions": 4,
      "changes": 6,
      "blob_url": "https://github.com/pytorch/pytorch/blob/1f213fa7400fdb76e7ff3d4c6809b826f09c88c0/torch%2Fcsrc%2Finductor%2Faoti_runtime%2Fsycl_runtime_wrappers.h",
      "raw_url": "https://github.com/pytorch/pytorch/raw/1f213fa7400fdb76e7ff3d4c6809b826f09c88c0/torch%2Fcsrc%2Finductor%2Faoti_runtime%2Fsycl_runtime_wrappers.h",
      "contents_url": "https://api.github.com/repos/pytorch/pytorch/contents/torch%2Fcsrc%2Finductor%2Faoti_runtime%2Fsycl_runtime_wrappers.h?ref=1f213fa7400fdb76e7ff3d4c6809b826f09c88c0",
      "patch": "@@ -128,12 +128,10 @@ static std::unique_ptr<sycl::kernel> _createKernel(\n     uint32_t numWarps,\n     uint32_t sharedMemory,\n     void** params,\n-    sycl::queue* queuePtr) {\n+    sycl::queue* queuePtr,\n+    uint32_t threadsPerWarp) {\n   std::string kernelName =\n       kernelPtr->get_info<sycl::info::kernel::function_name>();\n-  // Currently threadsPerWarp is hard code to 32 from torch.compile to triton\n-  // stack.\n-  int threadsPerWarp = 32;\n   uint32_t numParams = kernelPtr->get_info<sycl::info::kernel::num_args>();\n   size_t globalRangeX = gridX * threadsPerWarp * numWarps;\n   size_t globalRangeY = gridY;"
    }
  ],
  "source_page": "sources/prs/pytorch/PR-163388.md"
}